jump_starter/__init__.py
jump_starter/_version.py
jump_starter/models.py
jump_starter/py.typed
jump_starter/questionnaire.py
jump_starter/views/__init__.py
jump_starter/views/output_box.css
jump_starter/views/output_box.html.jinja
jump_starter/views/question_box.css
lf_jump_starter-0.1.1.dist-info/licenses/LICENSE
lf_jump_starter-0.1.1.dist-info/METADATA
lf_jump_starter-0.1.1.dist-info/WHEEL
lf_jump_starter-0.1.1.dist-info/top_level.txt
lf_jump_starter-0.1.1.dist-info/RECORD
