Metadata-Version: 2.4
Name: lf-jump-starter
Version: 0.1.1
Author-email: lincc-frameworks <seanmcgu@andrew.cmu.edu>
License: MIT License
Project-URL: Source Code, https://github.com/lincc-frameworks/jump-starter
Classifier: Development Status :: 4 - Beta
Classifier: License :: OSI Approved :: MIT License
Classifier: Intended Audience :: Developers
Classifier: Intended Audience :: Science/Research
Classifier: Operating System :: OS Independent
Classifier: Programming Language :: Python
Requires-Python: >=3.10
License-File: LICENSE
Requires-Dist: ipywidgets>=8.0
Requires-Dist: pydantic>=2.0
Requires-Dist: pyyaml>=6.0
Requires-Dist: markdown>=3.4
Requires-Dist: pygments>=2.0
Requires-Dist: jinja2>=3.0
Provides-Extra: dev
Requires-Dist: jupyter; extra == "dev"
Requires-Dist: mypy; extra == "dev"
Requires-Dist: pre-commit; extra == "dev"
Requires-Dist: pytest; extra == "dev"
Requires-Dist: pytest-cov; extra == "dev"
Requires-Dist: pytest-mock; extra == "dev"
Requires-Dist: ruff; extra == "dev"
Requires-Dist: types-Markdown; extra == "dev"
Requires-Dist: types-PyYAML; extra == "dev"
Dynamic: license-file
